{
  "basics": {
    "name": "Noah Sano",
    "label": "Student",
    "picture": "https://github.com/SerialProgrammer808.png",
    "email": "asano47@hawaii.edu",
    "phone": "808-773-4157",
    "website": "https://SerialProgrammer808.github.io",
    "summary": "I am studying for a B.S. in Computer Science in the Department of Information and Computer Sciences at the University of Hawaii. I expect to graduate in Fall, 2027.",
    "location": { "address": "", "postalCode": "96826", "city": "Honolulu", "countryCode": "USA", "region": "Hawaii" },
    "profiles": [
      { "network": "github", "username": "SerialProgrammer808", "url": "http://github.com/SerialProgrammer" },
      { "network": "linkedin", "username": "Noah Asano", "url": "http://https://www.linkedin.com/in/noah-asano-9b1a24328/" },
    ]
  },
  "interests": [
    { "name": "Artifical Intelligence" },
    { "name": "Site Reliability" },
    { "name": "Web Development" },
  ],
  "skills": [
    {
      "name": "Languages and Frameworks",
      "keywords": [ "C", "C++", "Java", "Javascript", "Python" ]
    },
    {
      "name": "Toolsets/OS",
      "keywords": [ "MacOS", "Git/GitHub/Gitlab" ]
    }
  ],
  "education": [
    {
      "institution": "University of Hawaii, Honolulu, HI",
      "area": "Computer Science (expected Fall, 2027)",
      "studyType": "B.S.",
      "startDate": "2023-08-21",
      "endDate": "Present",
      "courses": [
      ]
    }
  ],
  "work": [
    {
      "company": "UH Manoa Study Abroad Center",
      "position": "Web Developer",
      "website": "",
      "startDate": "2025-08-08",
      "endDate": "Present",
      "summary": "",
      "highlights": [
        "Maintain, update, and oversee official Study Abroad Center website"
      ]
    },
    {
      "company": "Holocron Security",
      "position": "Software Engineering Intern",
      "website": "https://holocronsecurity.com/",
      "startDate": "2026-01-02",
      "endDate": "Present",
      "summary": "",
      "highlights": [
        "Write unit tests in Rust for Holocron Security's RapidFactory application"
      ]
    }
  ],
  "volunteer": [
    {
      "organization": "Center for Renewable Energy and Island Sustainability",
      "website": "http://manoa.hawaii.edu/reis",
      "position": "Software Developer",
      "startDate": "2016-01-01",
      "endDate": "Present",
      "summary": "Lead developer for weather sensing project",
      "highlights": [
        "Design firmware for distributed weather sensor network",
        "Maintain custom data collection and storage infrastructure"
      ]
    },
    {
      "organization": "",
      "website": "",
      "position": "Professional organization involvement",
      "startDate": "",
      "endDate": "",
      "summary": "",
      "highlights": [
        "Chair, ACM Manoa, 2016-Present",
        "Member, IEEE Student Branch, 2014-Present",
        "Webmaster/IT Officer, IEEE Student Branch, UH Manoa, 2012-2013"
      ]
    }
  ],
  "awards": [
    {
      "title": "B+ Scholarship",
      "date": "2013-Present",
      "awarder": "State of Hawaii",
      "summary": "Scholarships awarded to incoming freshmen and continuing students who complete a rigorous high school curriculum with a minimum overall GPA of 3.0 at a Hawai'i public school."
    },
    {
      "title": "First place",
      "date": "2015",
      "awarder": "University of Hawaii Micromouse Competition",
      "summary": "My team won first place in 2015.  See my portfolio site for more details."
    }
  ],
  "references": [
    {
      "name": "Available upon request"
    }
  ]
}
